{"name":"Log into the GSA website as createDepartment","id":"validate-login-with-different-users-admin;log-into-the-gsa-website-as-createdepartment","testSteps":[{"number":1,"description":"And The user login into environment COMP_HOME_PAGE","duration":63374,"startTime":"2019-04-30T12:56:19.678-04:00[America/New_York]","screenshots":[{"screenshot":"047ccd958191ce6881e73382ea5bd630dc89e229c448cf91b1a799daab6bc287.png"}],"result":"SUCCESS","precondition":false},{"number":2,"description":"And Click on department sign in link","duration":3915,"startTime":"2019-04-30T12:57:23.059-04:00[America/New_York]","screenshots":[{"screenshot":"0249d52a501dc842f21788175a3857b04aa1f8ff20a32420bad027c0097b226a.png"}],"result":"SUCCESS","precondition":false},{"number":3,"description":"And Click on department accept button","duration":5110,"startTime":"2019-04-30T12:57:26.976-04:00[America/New_York]","screenshots":[{"screenshot":"ab120734c5160dc1d3f67ddbce1ac0679d7495867a976a9def4a26cb2473be1e.png"}],"result":"SUCCESS","precondition":false},{"number":4,"description":"And Enters the department email id createDepartment","duration":6888,"startTime":"2019-04-30T12:57:32.087-04:00[America/New_York]","screenshots":[{"screenshot":"4a1ac226b633b142156737a2bc72eaf9b8b88d2fa2f302d7e3a14bbf1581258f.png"}],"result":"SUCCESS","precondition":false},{"number":5,"description":"And Enters the department password alertadminPassword1","duration":736,"startTime":"2019-04-30T12:57:38.976-04:00[America/New_York]","screenshots":[{"screenshot":"ac756883f413cc94111a8f016914005336dcd8e33f6cf20ca6b8114c97666c3b.png"}],"result":"SUCCESS","precondition":false},{"number":6,"description":"Then Click on department sign in button","duration":643,"startTime":"2019-04-30T12:57:39.714-04:00[America/New_York]","screenshots":[{"screenshot":"cf72c5aedc282566192545f5bce17cc782fb23501518fe3621638fcfa8f829e6.png"}],"result":"SUCCESS","precondition":false},{"number":7,"description":"And Receive your one time department password myEmail","duration":45841,"startTime":"2019-04-30T12:57:40.358-04:00[America/New_York]","screenshots":[{"screenshot":"acd21a71bb4fd57140141e5f3f5fbb3c1fc9949e7684f696610ec54b7a916947.png"}],"result":"SUCCESS","precondition":false},{"number":8,"description":"And Enters department one time access code","duration":662,"startTime":"2019-04-30T12:58:26.201-04:00[America/New_York]","screenshots":[{"screenshot":"85757a8194b4a9f20026ed3255b33488b2a18eb771dd14dde974a23c2ac432c6.png"}],"result":"SUCCESS","precondition":false},{"number":9,"description":"Then Click on department one time submit button","duration":634,"startTime":"2019-04-30T12:58:26.865-04:00[America/New_York]","screenshots":[{"screenshot":"c6155f235e698a588f41f6d4496028cb7e29ad0a0c14738fe48e4e3753cd2aed.png"}],"result":"SUCCESS","precondition":false}],"userStory":{"id":"validate-login-with-different-users-admin","storyName":"Validate login with different users admin","path":"src/test/resources/features/LoginDepartmentSubTierOfficeAdmin.feature","narrative":"         a) Super Admin\n         b) Department Admin\n         c) Sub Tier Admin\n         d) office Admin       ","type":"feature"},"featureTag":{"name":"Features/Validate login with different users admin","type":"feature"},"title":"Log into the GSA website as createDepartment","tags":[{"name":"Validate login with different users admin","type":"feature"},{"name":"LoginDepartmentSubTierOfficeAdminRunner","type":"tag"},{"name":"otp","type":"tag"}],"startTime":"2019-04-30T12:56:01.053-04:00[America/New_York]","duration":146475,"projectKey":"","sessionId":"46a553ccfa0841581cd2e5691c01c774","driver":"chrome","manual":false,"testSource":"Cucumber","result":"SUCCESS"}